dropland_sqla/__init__.py
dropland_sqla/engine.py
dropland_sqla/main.py
dropland_sqla/model.py
dropland_sqla-0.7.10.dist-info/entry_points.txt
dropland_sqla-0.7.10.dist-info/WHEEL
dropland_sqla-0.7.10.dist-info/METADATA
dropland_sqla-0.7.10.dist-info/RECORD
