Metadata-Version: 2.1
Name: dropland-sqla
Version: 0.7.10
Summary: 
License: MIT
Author: Max Plutonium
Author-email: plutonium.max@gmail.com
Maintainer: Max Plutonium
Maintainer-email: plutonium.max@gmail.com
Requires-Python: >=3.9,<4.0
Classifier: License :: OSI Approved :: MIT License
Classifier: Programming Language :: Python :: 3
Classifier: Programming Language :: Python :: 3.9
Classifier: Programming Language :: Python :: 3.10
Requires-Dist: SQLAlchemy[asyncio] (>=1.4,<2.0)
